maleo_workshop/__init__.py
maleo_workshop/db.py
maleo_workshop/constants/__init__.py
maleo_workshop/constants/scribe/__init__.py
maleo_workshop/constants/scribe/response.py
maleo_workshop/constants/scribe/scenario.py
maleo_workshop/enums/__init__.py
maleo_workshop/enums/scribe/__init__.py
maleo_workshop/enums/scribe/response.py
maleo_workshop/enums/scribe/scenario.py
maleo_workshop/models/__init__.py
maleo_workshop/models/responses/__init__.py
maleo_workshop/models/responses/scribe/__init__.py
maleo_workshop/models/responses/scribe/response.py
maleo_workshop/models/responses/scribe/scenario.py
maleo_workshop/models/schemas/__init__.py
maleo_workshop/models/schemas/general.py
maleo_workshop/models/schemas/scribe/__init__.py
maleo_workshop/models/schemas/scribe/response.py
maleo_workshop/models/schemas/scribe/scenario.py
maleo_workshop/models/tables/__init__.py
maleo_workshop/models/tables/scribe/__init__.py
maleo_workshop/models/tables/scribe/response.py
maleo_workshop/models/tables/scribe/scenario.py
maleo_workshop/models/transfers/__init__.py
maleo_workshop/models/transfers/general/__init__.py
maleo_workshop/models/transfers/general/scribe/__init__.py
maleo_workshop/models/transfers/general/scribe/response.py
maleo_workshop/models/transfers/general/scribe/scenario.py
maleo_workshop/models/transfers/parameters/__init__.py
maleo_workshop/models/transfers/parameters/client/__init__.py
maleo_workshop/models/transfers/parameters/client/scribe/__init__.py
maleo_workshop/models/transfers/parameters/client/scribe/response.py
maleo_workshop/models/transfers/parameters/client/scribe/scenario.py
maleo_workshop/models/transfers/parameters/general/__init__.py
maleo_workshop/models/transfers/parameters/general/scribe/__init__.py
maleo_workshop/models/transfers/parameters/general/scribe/response.py
maleo_workshop/models/transfers/parameters/general/scribe/scenario.py
maleo_workshop/models/transfers/parameters/service/__init__.py
maleo_workshop-0.0.3.dist-info/METADATA
maleo_workshop-0.0.3.dist-info/WHEEL
maleo_workshop-0.0.3.dist-info/top_level.txt
maleo_workshop-0.0.3.dist-info/RECORD
